scrape_google_trends
