Metadata-Version: 2.1
Name: scrape-google-trends
Version: 1.0.1
Summary: A python library to scrape search results of google trends
Home-page: UNKNOWN
Author: DataKund
Author-email: datakund@gmail.com
License: Apache License 2.0
Keywords: google trends python bot_studio automation search result scraper title description
Platform: UNKNOWN
License-File: LICENSE
